iaar_metric/__init__.py
iaar_metric/metric.py
iaar_metric-0.1.0.dist-info/METADATA
iaar_metric-0.1.0.dist-info/WHEEL
iaar_metric-0.1.0.dist-info/top_level.txt
iaar_metric-0.1.0.dist-info/zip-safe
iaar_metric-0.1.0.dist-info/RECORD
